{"stats":{"minecraft:mined":{"minecraft:sand":4},"minecraft:custom":{"minecraft:jump":51,"minecraft:time_since_rest":6414,"minecraft:leave_game":1,"minecraft:damage_dealt":9,"minecraft:deaths":1,"minecraft:crouch_one_cm":104,"minecraft:sprint_one_cm":13633,"minecraft:play_time":20485,"minecraft:damage_taken":240,"minecraft:time_since_death":91,"minecraft:walk_one_cm":26526,"minecraft:sneak_time":30,"minecraft:total_world_time":29721,"minecraft:fall_one_cm":627,"minecraft:fly_one_cm":15624},"minecraft:killed_by":{"minecraft:husk":1},"minecraft:used":{"ait:tardis_item":1},"minecraft:picked_up":{"minecraft:sand":4}},"DataVersion":3465}